{
  "looped":false,
  "manualFov":true,
  "markers":[
    {
      "fov":60,
      "movingEnd":true,
      "movingStart":true,
      "pos":{
        "x":-1122.55457,
        "y":-912.356567,
        "z":521.082703
      },
      "rot":{
        "z":-0.472776473,
        "w":0.825043559,
        "x":0.26852873,
        "y":0.153875574
      },
      "time":0,
      "trackPosition":false
    },
    {
      "fov":60,
      "movingEnd":true,
      "movingStart":true,
      "pos":{
        "x":-1133.57288,
        "y":-904.871338,
        "z":512.044128
      },
      "rot":{
        "z":-0.431736469,
        "w":0.872917891,
        "x":0.203649402,
        "y":0.100722954
      },
      "time":2,
      "trackPosition":false
    },
    {
      "fov":60,
      "movingEnd":true,
      "movingStart":true,
      "pos":{
        "x":-1140.68408,
        "y":-898.943848,
        "z":510.57959
      },
      "rot":{
        "z":-0.678162336,
        "w":0.732687891,
        "x":0.0419303179,
        "y":0.0388099253
      },
      "time":4,
      "trackPosition":false
    },
    {
      "fov":60,
      "movingEnd":true,
      "movingStart":true,
      "pos":{
        "x":-1146.39026,
        "y":-894.886292,
        "z":510.261932
      },
      "rot":{
        "z":-0.993813396,
        "w":0.106786788,
        "x":0.0032610544,
        "y":0.0303490702
      },
      "time":6,
      "trackPosition":false
    },
    {
      "cut":true,
      "fov":60,
      "movingEnd":true,
      "movingStart":true,
      "pos":{
        "x":-1153.39722,
        "y":-898.315186,
        "z":510.270355
      },
      "rot":{
        "z":-0.835199416,
        "w":-0.549823761,
        "x":-0.00641149981,
        "y":0.00973926671
      },
      "time":8,
      "trackPosition":false
    },
    {
      "fov":60,
      "movingEnd":true,
      "movingStart":true,
      "pos":{
        "x":-1191.76379,
        "y":-887.28009,
        "z":510.542328
      },
      "rot":{
        "z":-0.740486085,
        "w":0.667216837,
        "x":0.053976275,
        "y":0.0599035844
      },
      "time":8,
      "trackPosition":false
    },
    {
      "fov":60,
      "movingEnd":true,
      "movingStart":true,
      "pos":{
        "x":-1206.47607,
        "y":-892.827515,
        "z":509.46759
      },
      "rot":{
        "z":-0.648494244,
        "w":0.759942293,
        "x":0.0335319228,
        "y":0.0286143534
      },
      "time":10,
      "trackPosition":false
    },
    {
      "cut":true,
      "fov":60,
      "movingEnd":true,
      "movingStart":true,
      "pos":{
        "x":-1218.67004,
        "y":-891.616089,
        "z":509.724182
      },
      "rot":{
        "z":-0.458838403,
        "w":0.888362646,
        "x":-0.0148402415,
        "y":-0.00766496966
      },
      "time":12.5999994,
      "trackPosition":false
    },
    {
      "fov":60,
      "movingEnd":true,
      "movingStart":true,
      "pos":{
        "x":-1237.04187,
        "y":-822.862488,
        "z":526.506287
      },
      "rot":{
        "z":-0.558310926,
        "w":0.763716757,
        "x":0.261621952,
        "y":0.191257298
      },
      "time":12.5999994,
      "trackPosition":false
    },
    {
      "fov":60,
      "movingEnd":true,
      "movingStart":true,
      "pos":{
        "x":-1230.48706,
        "y":-806.367126,
        "z":527.899963
      },
      "rot":{
        "z":-0.603977025,
        "w":0.726729512,
        "x":0.251658261,
        "y":0.209150434
      },
      "time":14.5999994,
      "trackPosition":false
    },
    {
      "fov":60,
      "movingEnd":true,
      "movingStart":true,
      "pos":{
        "x":-1224.71631,
        "y":-781.177856,
        "z":530.422668
      },
      "rot":{
        "z":-0.641091406,
        "w":0.691211343,
        "x":0.244525641,
        "y":0.226794988
      },
      "time":16.5999994,
      "trackPosition":false
    },
    {
      "fov":60,
      "movingEnd":true,
      "movingStart":true,
      "pos":{
        "x":-1216.97217,
        "y":-743.847351,
        "z":534.95697
      },
      "rot":{
        "z":-0.667183101,
        "w":0.65964061,
        "x":0.243289441,
        "y":0.246071234
      },
      "time":18.5999994,
      "trackPosition":false
    },
    {
      "fov":60,
      "movingEnd":true,
      "movingStart":true,
      "pos":{
        "x":-1219.52161,
        "y":-713.859619,
        "z":534.95697
      },
      "rot":{
        "z":-0.708212554,
        "w":0.605744183,
        "x":0.235713258,
        "y":0.275586754
      },
      "time":20.5999994,
      "trackPosition":false
    },
    {
      "fov":60,
      "movingEnd":true,
      "movingStart":true,
      "pos":{
        "x":-1235.67676,
        "y":-661.80896,
        "z":534.95697
      },
      "rot":{
        "z":-0.831494629,
        "w":0.432933003,
        "x":0.160767481,
        "y":0.308771342
      },
      "time":23.4999986,
      "trackPosition":false
    }
  ],
  "name":"camPath2",
  "rotFixId":9,
  "version":"6"
}