{
  "additionalAttributes":{
    "difficulty":"medium",
    "vehicle":"choice"
  },
  "author":"BeamNG",
  "careerSetup":{
    "defaultStarKeys":[
      "justFinish",
      "bronzePoints",
      "silverPoints"
    ],
    "showInCareer":true,
    "showInFreeroam":false,
    "starOutroTexts":{},
    "starRewards":{
      "bronzePoints":[
        {
          "attributeKey":"money",
          "rewardAmount":1500
        },
        {
          "attributeKey":"beamXP",
          "rewardAmount":5
        },
        {
          "attributeKey":"motorsport",
          "rewardAmount":200
        },
        {
          "attributeKey":"adventurer",
          "rewardAmount":25
        }
      ],
      "bronzeTime":[
        {
          "attributeKey":"bonusStars",
          "rewardAmount":1
        }
      ],
      "goldPoints":[
        {
          "attributeKey":"bonusStars",
          "rewardAmount":1
        }
      ],
      "justFinish":[
        {
          "attributeKey":"money",
          "rewardAmount":1500
        },
        {
          "attributeKey":"beamXP",
          "rewardAmount":5
        },
        {
          "attributeKey":"motorsport",
          "rewardAmount":200
        },
        {
          "attributeKey":"adventurer",
          "rewardAmount":25
        }
      ],
      "silverPoints":[
        {
          "attributeKey":"money",
          "rewardAmount":1500
        },
        {
          "attributeKey":"beamXP",
          "rewardAmount":5
        },
        {
          "attributeKey":"motorsport",
          "rewardAmount":200
        },
        {
          "attributeKey":"adventurer",
          "rewardAmount":25
        }
      ]
    },
    "starsActive":{
      "bronzePoints":true,
      "bronzeTime":true,
      "goldPoints":true,
      "justFinish":true,
      "silverPoints":true
    }
  },
  "customAdditionalAttributes":{},
  "date":1655294174,
  "description":"missions.utah.crawl002.description",
  "devMission":false,
  "devNotes":{
    "devMission":false,
    "mode":"silent",
    "text":""
  },
  "grouping":{
    "id":"",
    "label":""
  },
  "missionType":"crawl",
  "missionTypeData":{
    "bronzePoints":50,
    "bronzeRecoveries":10,
    "bronzeTime":120,
    "camPath":true,
    "defaultLaps":1,
    "goldPoints":105,
    "goldTime":75,
    "hidesOriginalTimeTrialFile":"",
    "introText":"missions.crawl.general.introTipsRecoveryOnly",
    "isPoints":false,
    "obstacles":false,
    "propsName":"penalty_prop",
    "silverPoints":100,
    "silverRecoveries":2,
    "silverTime":100,
    "startScreenText":"missions.utah.crawl002.startScreen",
    "zoneDist":30
  },
  "name":"missions.utah.crawl002.title",
  "retryBehaviour":"infiniteRetries",
  "setupModules":{
    "timeOfDay":{
      "enabled":false
    },
    "traffic":{
      "enabled":false
    },
    "vehicles":{
      "enabled":true,
      "includePlayerVehicle":true,
      "prioritizePlayerVehicle":false,
      "vehicles":[
        {
          "config":"deserttruck_crawler_A",
          "configPath":"vehicles/pickup/deserttruck_crawler_A.pc",
          "model":"pickup"
        }
      ]
    }
  },
  "startCondition":{
    "type":"always"
  },
  "startTrigger":{
    "level":"utah",
    "pos":[
      -566.4324341,
      -239.4983521,
      173.0518188
    ],
    "radius":4,
    "rot":[
      0,
      0,
      -0.1929225574,
      0.9812140455
    ],
    "type":"coordinates"
  },
  "visibleCondition":{
    "type":"always"
  }
}