{
  "looped":false,
  "manualFov":true,
  "markers":[
    {
      "fov":60,
      "movingEnd":true,
      "movingStart":false,
      "pos":{
        "x":-923.0353394,
        "y":-924.8887939,
        "z":137.2768555
      },
      "rot":{
        "z":0.6185935736,
        "w":0.7827261686,
        "x":0.05368326604,
        "y":-0.04242623597
      },
      "time":0,
      "trackPosition":false
    },
    {
      "fov":60,
      "movingEnd":true,
      "movingStart":true,
      "pos":{
        "x":-924.1199341,
        "y":-925.3128052,
        "z":137.2491913
      },
      "rot":{
        "z":0.8741697669,
        "w":0.4790703058,
        "x":0.03820346296,
        "y":-0.06971066445
      },
      "time":7,
      "trackPosition":false
    },
    {
      "fov":60,
      "movingEnd":true,
      "movingStart":true,
      "pos":{
        "x":-924.777771,
        "y":-925.5473633,
        "z":137.2201843
      },
      "rot":{
        "z":0.9342835546,
        "w":-0.3492377102,
        "x":-0.02512104437,
        "y":-0.06720401347
      },
      "time":11,
      "trackPosition":false
    },
    {
      "fov":60,
      "movingEnd":true,
      "movingStart":true,
      "pos":{
        "x":-926.9511719,
        "y":-926.3693848,
        "z":137.059494
      },
      "rot":{
        "z":0.8831890225,
        "w":-0.4633244276,
        "x":-0.03384432197,
        "y":-0.06451404095
      },
      "time":15,
      "trackPosition":false
    },
    {
      "fov":60,
      "movingEnd":true,
      "movingStart":true,
      "pos":{
        "x":-965.0215454,
        "y":-950.3113403,
        "z":136.2427673
      },
      "rot":{
        "z":0.8733341098,
        "w":-0.4869768023,
        "x":-0.005782401655,
        "y":-0.01037003938
      },
      "time":21,
      "trackPosition":false
    },
    {
      "fov":60,
      "movingEnd":true,
      "movingStart":true,
      "pos":{
        "x":-968.8778687,
        "y":-952.8751831,
        "z":136.0673828
      },
      "rot":{
        "z":0.8587136269,
        "w":-0.5105594993,
        "x":-0.02250993252,
        "y":-0.03785961494
      },
      "time":27,
      "trackPosition":false
    },
    {
      "fov":60,
      "movingEnd":false,
      "movingStart":true,
      "pos":{
        "x":-969.2424927,
        "y":-954.4261475,
        "z":135.8489227
      },
      "rot":{
        "z":0.6993739009,
        "w":-0.7129558325,
        "x":-0.0361917913,
        "y":-0.03550233319
      },
      "time":35,
      "trackPosition":false
    }
  ],
  "name":"Utah - Race 2",
  "rotFixId":1,
  "version":"6"
}